epfml/__init__.py
epfml/bundle.py
epfml/config.py
epfml/store.py
epfml/vpn.py
epfml/cli/__init__.py
epfml/cli/bundle.py
epfml/cli/store.py
epfml/cli/subcommand.py
epfml_utils-0.0.13.dist-info/LICENSE
epfml_utils-0.0.13.dist-info/METADATA
epfml_utils-0.0.13.dist-info/WHEEL
epfml_utils-0.0.13.dist-info/entry_points.txt
epfml_utils-0.0.13.dist-info/top_level.txt
epfml_utils-0.0.13.dist-info/RECORD
