Metadata-Version: 2.1
Name: epfml-utils
Version: 0.0.13
Summary: Tools for experimentation at MLO
License: Apache License
Project-URL: homepage, https://github.com/epfml/epfml-utils
Project-URL: repository, https://github.com/epfml/epfml-utils
Requires-Python: >=3.7
License-File: LICENSE
Requires-Dist: typing-extensions (>4)
Requires-Dist: toml
Requires-Dist: pathspec (>0.9)
Requires-Dist: boto3
Provides-Extra: test
Requires-Dist: pytest ; extra == 'test'
